{
  "project_info": {
    "project_number": "25031496031",
    "firebase_url": "https://nhom6-f2a53-default-rtdb.firebaseio.com",
    "project_id": "nhom6-f2a53",
    "storage_bucket": "nhom6-f2a53.appspot.com"
  },
  "client": [
    {
      "client_info": {
        "mobilesdk_app_id": "1:25031496031:android:f84f7bac13dffa5f2ee6ea",
        "android_client_info": {
          "package_name": "com.example.quanlynhahang"
        }
      },
      "oauth_client": [
        {
          "client_id": "25031496031-ivimi1q9uhjhdt9flhmlq1276r7ml6eo.apps.googleusercontent.com",
          "client_type": 3
        }
      ],
      "api_key": [
        {
          "current_key": "AIzaSyB6QFc8Unuez5gXe7uMT11ppRycTtaf3bs"
        }
      ],
      "services": {
        "appinvite_service": {
          "other_platform_oauth_client": [
            {
              "client_id": "25031496031-ivimi1q9uhjhdt9flhmlq1276r7ml6eo.apps.googleusercontent.com",
              "client_type": 3
            }
          ]
        }
      }
    },
    {
      "client_info": {
        "mobilesdk_app_id": "1:25031496031:android:b89227ec3ad112f32ee6ea",
        "android_client_info": {
          "package_name": "com.huongdancode.nhom6_app"
        }
      },
      "oauth_client": [
        {
          "client_id": "25031496031-ivimi1q9uhjhdt9flhmlq1276r7ml6eo.apps.googleusercontent.com",
          "client_type": 3
        }
      ],
      "api_key": [
        {
          "current_key": "AIzaSyB6QFc8Unuez5gXe7uMT11ppRycTtaf3bs"
        }
      ],
      "services": {
        "appinvite_service": {
          "other_platform_oauth_client": [
            {
              "client_id": "25031496031-ivimi1q9uhjhdt9flhmlq1276r7ml6eo.apps.googleusercontent.com",
              "client_type": 3
            }
          ]
        }
      }
    }
  ],
  "configuration_version": "1"
}